mseep_schwab_mcp-0.1.4.dist-info/licenses/LICENSE
schwab_mcp/__init__.py
schwab_mcp/auth.py
schwab_mcp/cli.py
schwab_mcp/py.typed
schwab_mcp/server.py
schwab_mcp/tokens.py
schwab_mcp/tools/__init__.py
schwab_mcp/tools/account.py
schwab_mcp/tools/history.py
schwab_mcp/tools/options.py
schwab_mcp/tools/orders.py
schwab_mcp/tools/quotes.py
schwab_mcp/tools/registry.py
schwab_mcp/tools/tools.py
schwab_mcp/tools/transactions.py
schwab_mcp/tools/utils.py
mseep_schwab_mcp-0.1.4.dist-info/METADATA
mseep_schwab_mcp-0.1.4.dist-info/WHEEL
mseep_schwab_mcp-0.1.4.dist-info/entry_points.txt
mseep_schwab_mcp-0.1.4.dist-info/top_level.txt
mseep_schwab_mcp-0.1.4.dist-info/RECORD
